tests/__init__.py
tiyaro/__init__.py
tiyaro/main.py
tiyaro/version.py
tiyaro/api/__init__.py
tiyaro/api/status_update.py
tiyaro/cmds/__init__.py
tiyaro/cmds/clean.py
tiyaro/cmds/infer.py
tiyaro/cmds/init.py
tiyaro/cmds/push.py
tiyaro/cmds/test.py
tiyaro/common/__init__.py
tiyaro/common/constants.py
tiyaro/common/utils.py
tiyaro/handler/__init__.py
tiyaro/handler/cli_state.py
tiyaro/handler/model_manifest.py
tiyaro/handler/tiyaro_test_state.py
tiyaro/handler/utils.py
tiyaro/sdk/__init__.py
tiyaro/sdk/base_handler.py
tiyaro/sdk/test_utils/__init__.py
tiyaro/sdk/test_utils/util.py
tiyaro-0.0.8.dist-info/LICENSE
tiyaro-0.0.8.dist-info/METADATA
tiyaro-0.0.8.dist-info/WHEEL
tiyaro-0.0.8.dist-info/entry_points.txt
tiyaro-0.0.8.dist-info/top_level.txt
tiyaro-0.0.8.dist-info/RECORD
