Metadata-Version: 2.1
Name: tiyaro
Version: 0.0.8
Summary: Tiyaro Python Package Index
Home-page: https://github.com/pypa/sampleproject
Author: Venkat Raman, I-Jong Lin
Author-email: venkat@tiyaro.ai, ijonglin@tiyaro.ai
License: Apache License 2.0
Platform: any
Classifier: Programming Language :: Python :: 3
Classifier: License :: OSI Approved :: Apache Software License
Classifier: Operating System :: OS Independent
Requires-Python: >=3.6
License-File: LICENSE
Requires-Dist: Click (==8.0.4)
Requires-Dist: requests
Requires-Dist: PyYAML
Requires-Dist: marshmallow
Requires-Dist: validators
